mozarbot/__init__.py
mozarbot/sdk.py
mozarbot-0.1.9.dist-info/METADATA
mozarbot-0.1.9.dist-info/WHEEL
mozarbot-0.1.9.dist-info/RECORD
