Metadata-Version: 2.4
Name: mozarbot
Version: 0.1.9
Summary: SDK para automações do Mozarbot
Author-email: Marcel Zanluca <marcel.zanluca@gmail.com>
License-Expression: MIT
Requires-Python: >=3.10
Requires-Dist: requests
